setup.py
frequency_analyzer/__init__.py
frequency_analyzer/__main__.py
frequency_analyzer/app.py
frequency_analyzer.egg-info/PKG-INFO
frequency_analyzer.egg-info/SOURCES.txt
frequency_analyzer.egg-info/dependency_links.txt
frequency_analyzer.egg-info/entry_points.txt
frequency_analyzer.egg-info/requires.txt
frequency_analyzer.egg-info/top_level.txt
frequency_analyzer/bin/__init__.py
frequency_analyzer/bin/categorizer.py
frequency_analyzer/bin/filters.py
frequency_analyzer/bin/interpolator.py
frequency_analyzer/bin/matrix.py
frequency_analyzer/bin/sanitizer.py
frequency_analyzer/bin/timer.py