Metadata-Version: 1.0
Name: frequency-analyzer
Version: 1.0.post0
Summary: A command-line tool for isolating frequencies found in accelerometer data.
Home-page: https://github.com/TorkamaniLab/frequency_analyzer
Author: Brian Schrader
Author-email: brian@brianschrader.com
License: UNKNOWN
Platform: UNKNOWN
